brand_color_analyzer.py
brand_color_analyzer-1.1.1.dist-info/licenses/LICENSE
brand_color_analyzer-1.1.1.dist-info/METADATA
brand_color_analyzer-1.1.1.dist-info/WHEEL
brand_color_analyzer-1.1.1.dist-info/entry_points.txt
brand_color_analyzer-1.1.1.dist-info/top_level.txt
brand_color_analyzer-1.1.1.dist-info/RECORD
