Metadata-Version: 2.4
Name: brand-color-analyzer
Version: 1.1.1
Summary: A research-based tool for analyzing brand colors using color psychology and marketing research
Author-email: Michail Semoglou <m.semoglou@tongji.edu.cn>
License: MIT
Project-URL: Homepage, https://github.com/MichailSemoglou/brand-color-analyzer
Project-URL: Repository, https://github.com/MichailSemoglou/brand-color-analyzer
Project-URL: Bug Tracker, https://github.com/MichailSemoglou/brand-color-analyzer/issues
Project-URL: Documentation, https://github.com/MichailSemoglou/brand-color-analyzer#readme
Keywords: color psychology,brand analysis,marketing research,color theory,brand personality,emotional response,cultural associations,image analysis
Classifier: Development Status :: 5 - Production/Stable
Classifier: Intended Audience :: Developers
Classifier: Intended Audience :: Science/Research
Classifier: Intended Audience :: Education
Classifier: License :: OSI Approved :: MIT License
Classifier: Operating System :: OS Independent
Classifier: Programming Language :: Python :: 3
Classifier: Programming Language :: Python :: 3.8
Classifier: Programming Language :: Python :: 3.9
Classifier: Programming Language :: Python :: 3.10
Classifier: Programming Language :: Python :: 3.11
Classifier: Programming Language :: Python :: 3.12
Classifier: Topic :: Scientific/Engineering
Classifier: Topic :: Scientific/Engineering :: Image Recognition
Classifier: Topic :: Software Development :: Libraries :: Python Modules
Classifier: Topic :: Multimedia :: Graphics
Requires-Python: >=3.8
License-File: LICENSE
Requires-Dist: numpy>=1.20.0
Requires-Dist: Pillow>=9.0.0
Requires-Dist: matplotlib>=3.3.0
Requires-Dist: tqdm>=4.60.0
Dynamic: license-file
